tf_image-0.2.0-py3.9-nspkg.pth
tf_image/application/__init__.py
tf_image/application/augmentation_config.py
tf_image/application/tools.py
tf_image/core/__init__.py
tf_image/core/clip.py
tf_image/core/colors.py
tf_image/core/convert_type_decorator.py
tf_image/core/erase.py
tf_image/core/quality.py
tf_image/core/random.py
tf_image/core/resize.py
tf_image/core/bboxes/__init__.py
tf_image/core/bboxes/clip.py
tf_image/core/bboxes/erase.py
tf_image/core/bboxes/flip.py
tf_image/core/bboxes/resize.py
tf_image/core/bboxes/rotate.py
tf_image-0.2.0.dist-info/LICENSE
tf_image-0.2.0.dist-info/METADATA
tf_image-0.2.0.dist-info/WHEEL
tf_image-0.2.0.dist-info/namespace_packages.txt
tf_image-0.2.0.dist-info/top_level.txt
tf_image-0.2.0.dist-info/RECORD
