Metadata-Version: 2.1
Name: tf-image
Version: 0.2.0
Summary: Image augmentation operations for TensorFlow 2+.
Home-page: https://github.com/Ximilar-com/tf-image
Author: Ximilar.com Team, Michal Lukac, Libor Vanek, ...
Author-email: tech@ximilar.com
License: MIT
Keywords: machine learning,multimedia,image
Platform: UNKNOWN
Classifier: Development Status :: 3 - Alpha
Classifier: License :: OSI Approved :: MIT License
Classifier: Programming Language :: Python :: 3.6
Classifier: Topic :: Scientific/Engineering :: Artificial Intelligence
